<?xml version="1.0" encoding="UTF-8"?>
<openerp>
	<data>
 		<record id="view_oemedical_patient_tree" model="ir.ui.view"> 
 			<field name="name">oemedical.patient.tree</field> 
 			<field name="model">oemedical.patient</field> 
 			<field name="priority" eval="8" /> 
 			<field name="arch" type="xml"> 
 				<tree string="Oemedical Patient"> 
 					<field name="name" />
<!-- 					<field name="lastname" />-->
 					<field name="ssn" /> 
 					<field name="identification_code" /> 
 					<field name="age" />
 					<field name="sex" /> 
 				</tree> 
 			</field> 
 		</record> 

 		<record id="view_oemedical_patient_form" model="ir.ui.view"> 
 			<field name="name">oemedical.patient.form</field> 
 			<field name="model">oemedical.patient</field> 
 			<field name="priority" eval="8" /> 
 			<field name="arch" type="xml"> 
 			 <form string="Patient" version="7.0"> 
                    <sheet> 
                        <div>
                            <field name="photo" widget='image' class="oe_left oe_avatar"/> 
                            <div> 
                                 <h1> 
		                            <field name="first_name" placeholder="First Name" style="width: 20%%" on_change="onchange_name(first_name, lastname, slastname, context)"  /> 
		                            <field name="lastname" placeholder="Last Name" style="width: 20%%" on_change="onchange_name(first_name, lastname, slastname, context)" /> 
		                            <field name="slastname" placeholder="S Last Name" style="width: 20%%" on_change="onchange_name(first_name, lastname, slastname, context)" /> 
	                            </h1> 
                            </div> 
     						<div> 
     							<label for="sex" class="oe_edit_only"/> 
     							<field name="sex" style="width: 30%%"/> 
     							<label for="ssn"/> 
     							<field name="ssn" style="width: 20%%"/> 
     							<label for="identification_code"/> 
     							<field name="identification_code" style="width: 17%%" attrs="{'readonly': True }"/> 
     						</div> 
     						<div> 
     							<field name="name" invisible="1"/> 
     						</div> 
                            <div>
     							<label for="dob"/> 
     							<field name="dob" style="width: 30%%"/> 
     							<label for="age"/> 
     							<field name="age" style="width: 30%%"/> 
                            </div> 
                        </div>
                    <notebook> 
                        <page string="General Information"> 
                            <group  col="6" colspan="4"> 
     							<field name="blood_type" style="width: 8%%"/> 
     							<field name="rh" nolabel="1"/> 
               					<field name="ethnic_group" /> 
                            </group>
                            <group string="Contact Information">
                                <group>
                                    <label for="street" string="Address"/>
                                    <div>
                                        <field name="use_parent_address" class="oe_edit_only oe_inline" invisible="1"/>
                                        <label for="use_parent_address" class="oe_edit_only" invisible="1"/>
                                        <field name="street" placeholder="Street..." />
                                        <field name="street2" />
                                        <div class="address_format">
                                            <field name="city" placeholder="City" style="width: 40%%" />
                                            <field name="state_id" class="oe_no_button" placeholder="State" style="width: 37%%" options='{"no_open": True}' />
                                            <field name="zip" placeholder="ZIP" style="width: 20%%" />
                                        </div>
                                        <field name="country_id" placeholder="Country" class="oe_no_button" options='{"no_open": True}' />
                                    </div>
                                    <field name="website" widget="url" placeholder="e.g. www.openerp.com"/>
                                </group>
                                <group>
                                    <field name="phone" placeholder="e.g. +32.81.81.37.00"/>
                                    <field name="mobile"/>
                                    <field name="fax"/>
                                    <field name="email" widget="email"/>
                                </group>
                            </group>
                            <group  col="4" colspan="4"> 
             					<field name="marital_status" colspan="2"/> 
             					<field name="family" invisivle="1" colspan="2"/> 
                                <group colspan="4" col="4">
                 					<field name="primary_care_doctor" />
                 					<field name="current_insurance" /> 
                                </group>
                                <separator colspan="4" string="Patient Allergies and Critical Information"/>
             					<field name="critical_info" colspan="4" nolabel="1"/> 
             				</group> 
         				</page> 
                        <page string="Medication" >
<!-- Patient Medications -->
                            <separator string="Medications" colspan="4"/>
          					<field name="medications"  nolabel="1" colspan="4">  
			                    <tree string="Oemedical Patient Medication">
				                    <field name="doctor" />
				                    <field name="adverse_reaction" />
				                    <field name="notes" />
				                    <field name="is_active" />
				                    <field name="course_completed" />
				                    <field name="template" />
				                    <field name="discontinued_reason" />
				                    <field name="discontinued" />
			                    </tree>
			                    <form string="Oemedical Patient Medication">
				                    <field name="doctor" />
				                    <field name="adverse_reaction" />
				                    <field name="notes" />
				                    <field name="is_active" />
				                    <field name="course_completed" />
				                    <field name="template" />
				                    <field name="discontinued_reason" />
				                    <field name="discontinued" />
			                    </form>
                            </field>
<!-- Patient Vaccinations -->
                            <separator string="Vaccinations" colspan="4"/>
          					<field name="vaccinations"  nolabel="1" colspan="4"> 
			                    <tree string="Oemedical Vaccination">
				                    <field name="name" />
				                    <field name="vaccine_lot" />
				                    <field name="patient_id" />
				                    <field name="vaccine" />
				                    <field name="dose" />
				                    <field name="observations" />
				                    <field name="date" />
				                    <field name="institution" />
				                    <field name="next_dose_date" />
			                    </tree>
			                    <form string="Oemedical Vaccination">
				                    <field name="name" />
				                    <field name="vaccine_lot" />
				                    <field name="patient_id" />
				                    <field name="vaccine" />
				                    <field name="dose" />
				                    <field name="observations" />
				                    <field name="date" />
				                    <field name="institution" />
				                    <field name="next_dose_date" />
			                    </form>
                            </field>

                        </page>

<!-- Patient Diseases -->
                        <page string="Diseases" >
                                <separator string="Diseases" colspan="4"/>
              					<field name="diseases"  nolabel="1" colspan="4">  
				                    <tree string="Oemedical Patient Disease">
					                    <field name="treatment_description" />
					                    <field name="healed_date" />
					                    <field name="pathology" />
					                    <field name="is_allergy" />
					                    <field name="doctor" />
					                    <field name="pregnancy_warning" />
					                    <field name="weeks_of_pregnancy" />
					                    <field name="is_on_treatment" />
					                    <field name="diagnosed_date" />
				                    </tree>
				                    <form string="Oemedical Patient Disease">
					                    <field name="treatment_description" />
					                    <field name="healed_date" />
					                    <field name="pathology" />
					                    <field name="is_allergy" />
					                    <field name="doctor" />
					                    <field name="pregnancy_warning" />
					                    <field name="weeks_of_pregnancy" />
					                    <field name="is_on_treatment" />
					                    <field name="diagnosed_date" />
					                    <field name="extra_info" />
					                    <field name="is_active" />
					                    <field name="date_stop_treatment" />
					                    <field name="pcs_code" />
					                    <field name="is_infectious" />
					                    <field name="patient_id" />
					                    <field name="age" />
					                    <field name="date_start_treatment" />
					                    <field name="short_comment" />
				                    </form>
                                </field>
                        </page>
                        <page string="Misc">
                            <group colspan="4" col="4">
                                <separator colspan="4" string="Patient Extra Information"/>
              					<field name="general_info" nolabel="1"  colspan="4"/> 
                            </group>
                            <newline/>
                            <group colspan="4" col="6">
                                <field name="deceased"/>
                                <field name="dod" attrs="{'invisible':[('deceased','=',False)],'required':[('deceased','=',True)]}"/>
                                <field name="cod" attrs="{'invisible':[('deceased','=',False)]}"/>
                            </group>
                        </page>
                    </notebook> 
 				</sheet> 
 				</form> 
 			</field> 
 		</record> 

        <record model="ir.ui.view" id="view_oemedical_patient_kanban">
            <field name="name">oemedical.patient.kanban</field>
            <field name="model">oemedical.patient</field>
            <field name="type">kanban</field>
            <field name="arch" type="xml">
                <kanban>
                    <templates>
                            <field name="name"/>
                        <t t-name="kanban-box">
                            <div class="oe_employee_vignette">
                                <div class="oe_employee_image">
                                    <a type="open"><img t-att-src="kanban_image('oemedical.patient', 'photo', record.id.value)" width="175" height="140" class="oe_employee_picture"/></a>
                                </div>
                                <div class="oe_employee_details">
                                    <h3>
                                        <a type="open"><field name="name"/></a>
                                    </h3>
                                    <ul>
                                        <li t-if="record.age.raw_value">Age: <field name="age"/></li>
                                        <li t-if="record.sex.raw_value">Sex: <field name="sex"/></li>
                                        <li t-if="record.blood_type.raw_value">Blond: <field name="blood_type"/><field name="rh"/></li>
                                        <li t-if="record.ssn.raw_value">SSN: <field name="ssn"/></li>
                                    </ul>
                                </div>
                            </div>
                        </t>
                    </templates>
                </kanban>
            </field>
        </record>

 		<record id="view_oemedical_patient_search" model="ir.ui.view"> 
 			<field name="name">oemedical.patient.search</field> 
 			<field name="model">oemedical.patient</field> 
 			<field name="priority" eval="8" /> 
 			<field name="arch" type="xml"> 
 				<search string="Oemedical Patient"> 
 					<field name="name" /> 
 					<field name="family" /> 
 					<field name="general_info" /> 
 					<field name="primary_care_doctor" /> 
 					<field name="childbearing_age" /> 
 					<field name="critical_info" /> 
 					<field name="lastname" /> 
 					<field name="ethnic_group" /> 
 					<field name="ssn" /> 
 					<field name="dob" /> 
 					<field name="age" /> 
 					<field name="dod" /> 
 					<field name="current_insurance" /> 
 					<field name="cod" /> 
 					<field name="identification_code" /> 
 					<field name="deceased" /> 
 					<newline /> 
 					<group expand="0" string="Group By...">  
 						<filter string="SSN" domain="[]" context="{'group_by':'ssn'}" /> 
 						<filter string="DoB" domain="[]" context="{'group_by':'dob'}" /> 
 						<filter string="Age" domain="[]" context="{'group_by':'age'}" /> 
 						<filter string="Date of Death" domain="[]" context="{'group_by':'dod'}" /> 
 						<filter string="Insurance" domain="[]" context="{'group_by':'current_insurance'}" /> 
 						<filter string="Cause of Death" domain="[]" context="{'group_by':'cod'}" /> 
 						<filter string="ID" domain="[]" context="{'group_by':'identification_code'}" /> 
 						<filter string="Deceased" domain="[]" context="{'group_by':'deceased'}" /> 
 					</group> 
 				</search> 
 			</field> 
 		</record> 

 		<record model="ir.actions.act_window" id="act_open_oemedical_patient_view"> 
 			<field name="name">Patient</field> 
 			<field name="type">ir.actions.act_window</field> 
 			<field name="res_model">oemedical.patient</field> 
 			<field name="view_type">form</field> 
 			<field name="view_mode">tree,form,kanban</field> 
 			<field name="search_view_id" ref="view_oemedical_patient_search" /> 
 			<field name="domain">[]</field> 
 			<field name="context">{}</field> 
 		</record> 

 		<record model="ir.actions.act_window.view" id="act_open_oemedical_patient_view_form"> 
 			<field name="act_window_id" ref="act_open_oemedical_patient_view" /> 
 			<field name="sequence" eval="20" /> 
 			<field name="view_mode">form</field> 
 			<field name="view_id" ref="view_oemedical_patient_form" /> 
 		</record> 

 		<record model="ir.actions.act_window.view" id="act_open_oemedical_patient_view_tree"> 
 			<field name="act_window_id" ref="act_open_oemedical_patient_view" /> 
 			<field name="sequence" eval="10" /> 
 			<field name="view_mode">tree</field> 
 			<field name="view_id" ref="view_oemedical_patient_tree" /> 
 		</record> 

 		<record model="ir.actions.act_window.view" id="act_open_oemedical_patient_view_kanban"> 
 			<field name="act_window_id" ref="act_open_oemedical_patient_view" /> 
 			<field name="sequence" eval="20" /> 
 			<field name="view_mode">kanban</field> 
 			<field name="view_id" ref="view_oemedical_patient_kanban" /> 
 		</record> 


	</data>
</openerp>
