<?xml version="1.0" encoding="utf-8"?>
<!-- Copyright 2016 LasLabs Inc.
     License AGPL-3.0 or later (http://www.gnu.org/licenses/agpl). -->

<odoo>
    
    <record id="pathology_code_01" model="medical.pathology.code.type">
        <field name="name">ICD9CM Disease/Injury</field>
    </record>
    
    <record id="pathology_code_02" model="medical.pathology.code.type">
        <field name="name">ICD9CM Procedures</field>
    </record>
    
    <record id="pathology_code_03" model="medical.pathology.code.type">
        <field name="name">ICD9CM V-Code</field>
    </record>
    
    <record id="pathology_code_04" model="medical.pathology.code.type">
        <field name="name">ICD9CM E-Code</field>
    </record>
    
    <record id="pathology_code_05" model="medical.pathology.code.type">
        <field name="name">ICD10CM</field>
    </record>
    
    <record id="pathology_code_06" model="medical.pathology.code.type">
        <field name="name">ICD10PCS</field>
    </record>
    
    <record id="pathology_code_07" model="medical.pathology.code.type">
        <field name="name">ICD10AM 6th Edition</field>
    </record>
    
</odoo>
